frog.cpython-312-x86_64-linux-gnu.so
python_frog-0.6.11.dist-info/RECORD
python_frog-0.6.11.dist-info/METADATA
python_frog-0.6.11.dist-info/WHEEL
python_frog-0.6.11.dist-info/top_level.txt
python_frog-0.6.11.dist-info/LICENSE
python_frog-0.6.11.data/data/sources/frog_wrapper.pyx
python_frog.libs/libicui18n-4fcc01ea.so.60.3
python_frog.libs/libmbt-c95d3232.so.2.0.0
python_frog.libs/libticcutils-9592988c.so.10.0.0
python_frog.libs/libfrog-a7a60018.so.3.0.0
python_frog.libs/libxml2-218173d1.so.2.9.7
python_frog.libs/libicudata-05640f77.so.60.3
python_frog.libs/liblzma-51a76f52.so.5.2.4
python_frog.libs/libgomp-24e2ab19.so.1.0.0
python_frog.libs/libfolia-5b9daa97.so.22.0.0
python_frog.libs/libbz2-e3e8e7e8.so.1.0.6
python_frog.libs/libtimbl-d4503661.so.7.0.0
python_frog.libs/libicuio-eb73b59c.so.60.3
python_frog.libs/libucto-4685ebf0.so.6.0.0
python_frog.libs/libexttextcat-2-dcaa456e.0.so.0.0.0
python_frog.libs/libicuuc-14201aad.so.60.3
