Metadata-Version: 2.1
Name: python-frog
Version: 0.6.11
Summary: Python binding to Frog, an NLP suite for Dutch doing part-of-speech tagging, lemmatisation, morphological analysis, named-entity recognition, shallow parsing, and dependency parsing.
Home-page: https://github.com/proycon/python-frog
Author: Maarten van Gompel
Author-email: proycon@anaproy.nl
License: GPLv3
Keywords: nlp computational_linguistics dutch pos lemmatizer
Classifier: Development Status :: 5 - Production/Stable
Classifier: Topic :: Text Processing :: Linguistic
Classifier: Programming Language :: Cython
Classifier: Programming Language :: Python :: 3
Classifier: Operating System :: POSIX
Classifier: Intended Audience :: Developers
Classifier: Intended Audience :: Science/Research
Classifier: License :: OSI Approved :: GNU General Public License v3 (GPLv3)
Requires: frog (>=0.30)
Requires: ucto (>=0.29)
License-File: LICENSE
Requires-Dist: Cython
